LICENSE.txt
README.rst
pyproject.toml
openet/.DS_Store
openet/__init__.py
openet/sims/__init__.py
openet/sims/collection.py
openet/sims/data.py
openet/sims/image.py
openet/sims/interpolate.py
openet/sims/model.py
openet/sims/utils.py
openet/sims/tests/conftest.py
openet/sims/tests/ee_wb_valid.csv
openet/sims/tests/test_a_utils.py
openet/sims/tests/test_b_data.py
openet/sims/tests/test_b_model.py
openet/sims/tests/test_c_image.py
openet/sims/tests/test_d_collection.py
openet/sims/tests/test_d_interpolate.py
openet/sims/tests/.pytest_cache/.gitignore
openet/sims/tests/.pytest_cache/CACHEDIR.TAG
openet/sims/tests/.pytest_cache/README.md
openet/sims/tests/.pytest_cache/v/cache/lastfailed
openet/sims/tests/.pytest_cache/v/cache/nodeids
openet/sims/tests/.pytest_cache/v/cache/stepwise
openet_sims.egg-info/PKG-INFO
openet_sims.egg-info/SOURCES.txt
openet_sims.egg-info/dependency_links.txt
openet_sims.egg-info/requires.txt
openet_sims.egg-info/top_level.txt