Metadata-Version: 2.1
Name: openet-sims
Version: 0.2.6
Summary: Earth Engine implementation of the SIMS model
Author-email: Alberto Guzman <aguzman@csumb.edu>
License:                                  Apache License
Project-URL: Homepage, https://github.com/Open-ET/openet-sims
Keywords: SIMS,OpenET,Earth Engine,Evapotranspiration,Landsat
Classifier: Programming Language :: Python :: 3
Classifier: License :: OSI Approved :: Apache Software License
Classifier: Operating System :: OS Independent
Requires-Python: >=3.8
License-File: LICENSE.txt
Requires-Dist: earthengine-api>=0.1.392
Requires-Dist: openet-core>=0.6.0
Provides-Extra: test
Requires-Dist: pytest; extra == "test"
Requires-Dist: pandas; extra == "test"
